{"contradiction": [{"uid": "chinese-35905-val", "text_a": "\u76f4\u5230 \u7f8e\u56fd \u63a5\u7ba1 \u4e3a\u6b62 \uff0c \u5e93 \u83b1 \u5e03\u62c9 \u4ee5\u524d \u88ab \u79f0\u4e3a \u897f\u73ed\u7259 \u7ef4\u5c14\u4eac \u7fa4\u5c9b \uff0c \u5b83 \u4f4d\u4e8e \u5728 \u6ce2\u591a\u9ece\u5404 \u548c \u5723\u6258\u9a6c\u65af \u4e4b\u95f4 \u7684 \u7f8e\u5c5e \u7ef4\u5c14\u4eac \u7fa4\u5c9b \u3002", "label": "contradiction", "portion_identifier": -1, "text_b": "\u5e93 \u83b1 \u5e03\u62c9 \u5c9b \u4f4d\u4e8e \u6ce2\u591a\u9ece\u5404 \u548c \u7f8e\u5c5e \u7ef4\u5c14\u4eac \u7fa4\u5c9b \u4e2d \u7684 \u5723\u6258\u9a6c\u65af \u5c9b \u4e4b\u95f4 \u7684 \u67d0\u5904 \u3002"}, {"uid": "chinese-37026-val", "text_a": "\u8fd9 \u4e00 \u63d0\u8bae \u6700\u521d \u5f15\u8d77 \u4e86 \u4e00\u4e9b \u8bc4\u8bba\u5bb6 \u7684 \u5632\u7b11 , \u4ed6\u4eec \u5bf9 \u798f\u5e03\u65af \u7684 \u8511\u89c6 \u662f \u76f8\u5f53 \u660e\u663e\u7684 \u3002", "label": "contradiction", "portion_identifier": -1, "text_b": "\u798f\u5e03\u65af \u53ea\u6709 \u652f\u6301\u8005 \u3002"}], "entailment": [{"uid": "chinese-35265-val", "text_a": "\u51e0 \u5e74 \u524d \uff0c \u6211 \u8fd8\u662f \u90a3\u91cc \u4e00 \u540d \u5b66\u751f \uff0c \u5e76\u4e14 \u53bb \u4f26\u6566 \u5b66\u4e60 \u4e86 \u4e00\u4e2a \u5b66\u671f \u3002", "label": "entailment", "portion_identifier": -1, "text_b": "\u51e0 \u5e74 \u524d \uff0c \u6211 \u5728 \u4f26\u6566 \u5b66\u4e60 \u4e86 \u4e00\u4e2a \u5b66\u671f \u3002"}, {"uid": "chinese-35809-val", "text_a": "\u201c \u795d \u4f60 \u597d\u8fd0 \uff0c \u5148\u751f \uff0c \u201d \u94c1\u8840 \u8239\u957f \u6109\u5feb\u5730 \u5411 \u4ed6 \u6253\u62db\u547c \u3002", "label": "entailment", "portion_identifier": -1, "text_b": "Blood \u795d \u7537\u5b50 \u65e5\u5b89 \u3002"}], "neutral": [{"uid": "chinese-37289-val", "text_a": "\u5f53\u7136 \uff0c \u970d \u683c\u74e6\u4ec0 \u8ba4\u4e3a \u8bed\u8a00 \u662f \u201c \u6beb\u65e0 \u4ef7\u503c \uff0c \u4ee4\u4eba\u6076\u5fc3 \u5e76\u4e14 \u4e0d \u9002\u5408 \u4eba\u7c7b \u4f7f\u7528 \u7684 \u201d \uff0c \u5c31 \u50cf \u732a\u98df \u4e00\u6837 \u3002", "label": "neutral", "portion_identifier": -1, "text_b": "\u201c Hogwash \u201d \u8fd9 \u8bcd \u7684 \u672c\u610f \u662f \u6d17 \u732a \u65f6 \u5269\u4e0b \u7684 \u810f \u6c34 \uff0c \u73b0\u5728 \u6bd4\u55bb \u5e9f\u8bdd \u3002"}, {"uid": "chinese-35192-val", "text_a": "\u662f\u7684 \uff0c \u4ed6\u4eec \u6709 \u4e00 \u5927 \u5806 \u540c\u65f6 \u574f\u6389 \u7684 \u4e1c\u897f", "label": "neutral", "portion_identifier": -1, "text_b": "\u4e00\u4e9b \u88ab \u6253\u788e \u7684 \u4e1c\u897f \u662f \u8d35\u91cd\u7269\u54c1 \u3002"}]}