{"contradiction": [{"uid": "spanish-12730-val", "text_a": "preoc\u00fapate por c\u00f3mo afectan las noticias nacionales a la zona local", "label": "contradiction", "portion_identifier": -1, "text_b": "No podria importarme menos lo que las noticias nacionales cubren con respecto a nuestras areas locales"}], "entailment": [{"uid": "spanish-13812-val", "text_a": "En este h\u00edbrido , el presidente ejecutivo asigna el control central a un CIO corporativo y una organizaci\u00f3n CIO , a la vez que delega autoridad espec\u00edfica a cada unidad de negocio para gestionar sus propios y \u00fanicos requisitos de gesti\u00f3n de informaci\u00f3n .", "label": "entailment", "portion_identifier": -1, "text_b": "Un director general de soporte y un director general corporativo podr\u00edan compartir el control de una compa\u00f1\u00eda en algunas organizaciones ."}], "neutral": [{"uid": "spanish-12915-val", "text_a": "s\u00ed , bueno , no es que no sea legal llevar una pistola en Texas , no lo es , pero puedes tenerla en tu casa", "label": "neutral", "portion_identifier": -1, "text_b": "Es un delito tener una pistola en p\u00fablico en Texas ."}]}