{"contradiction": [{"uid": "vietnamese-34236-val", "text_a": "C\u00e1c ch\u01b0\u01a1ng tr\u00ecnh c\u1ee7a b\u1ea1n b\u00e8 nh\u01b0 c\u00e1c nh\u00e0 l\u00e3nh \u0111\u1ea1o th\u01b0 vi\u1ec7n tr\u1ebb v\u00e0 tu\u1ea7n t\u00ecnh y\u00eau \u0111ang \u0111\u1ecdc c\u00f9ng nhau nh\u1eafm \u0111\u1ebfn nh\u1eefng ng\u01b0\u1eddi tr\u1ebb tu\u1ed5i v\u00e0 th\u1ea5m nhu\u1ea7n th\u00f3i quen th\u01b0 vi\u1ec7n khi c\u00f2n nh\u1ecf .", "label": "contradiction", "portion_identifier": -1, "text_b": "C\u00e1c ch\u01b0\u01a1ng tr\u00ecnh t\u1eadp trung v\u00e0o vi\u1ec7c \u0111\u01b0a tr\u1ebb em ra ngo\u00e0i ch\u01a1i ."}], "entailment": [{"uid": "vietnamese-33117-val", "text_a": "Anh \u1ea5y quay l\u1ea1i v\u1edbi Ch\u00faa Julian .", "label": "entailment", "portion_identifier": -1, "text_b": "Anh mu\u1ed1n h\u1ecfi Ch\u00faa Julian m\u1ed9t \u0111i\u1ec1u g\u00ec \u0111\u00f3 ."}], "neutral": [{"uid": "vietnamese-34043-val", "text_a": "H\u1ecd b\u00e0n lu\u1eadn v\u1ec1 c\u00e1c m\u1ee5c ti\u00eau trong ng\u00f4n ng\u1eef \u0111\u00e3 \u0111\u01b0\u1ee3c m\u00e3 h\u00f3a , gi\u1ea3 v\u1edd l\u00e0 sinh vi\u00ean \u0111\u1ec3 th\u1ea3o lu\u1eadn v\u1ec1 c\u00e1c l\u0129nh v\u1ef1c ki\u1ebfn tr\u00fac kh\u00e1c nhau \u0111\u01b0\u1ee3c g\u1ecdi l\u00e0 Trung t\u00e2m Th\u01b0\u01a1ng m\u1ea1i Th\u1ebf gi\u1edbi , ngh\u1ec7 thu\u1eadt L\u1ea7u N\u0103m G\u00f3c , lu\u1eadt Capitol , v\u00e0 to\u00e0 nh\u00e0 ch\u00ednh tr\u1ecb Nh\u00e0 Tr\u1eafng .", "label": "neutral", "portion_identifier": -1, "text_b": "H\u1ecd n\u00f3i v\u1ec1 nh\u1eefng m\u1ee5c ti\u00eau m\u00e0 h\u1ecd mu\u1ed1n th\u1ed5i tung l\u00ean b\u1eb1ng gi\u1ea3i m\u00e3 ."}]}