{"0": [{"uid": "korean-861-val", "text_a": "\uadf8\uac83\uc740 \ucf54\ub124\ud2f0\ucef7\uc8fc\uc5d0\uc11c \uba78\uc885 \uc704\uae30\uc5d0 \uc788\uace0 \ubc84\ubaac\ud2b8\uc8fc\uc5d0\uc11c \uba78\uc885 \uc704\uae30\uc5d0 \uac00\uae4c\uc6cc\uc838 \uc788\uc73c\uba70 \ub85c\ub4dc\uc544\uc77c\ub79c\ub4dc\uc8fc\uc5d0\uc11c\ub294 \uacfc\uac70\uc5d0 \uc0b4\uc558\ub358 \uae30\ub85d\uc774 \uc788\uace0 \ub9e4\uc0ac\ucd94\uc138\uce20\uc8fc\uc640 \ub274\ud584\ud504\uc154\uc8fc\uc5d0\uc11c\ub294 \uba78\uc885 \uc704\uae30\uc5d0 \uac00\uae5d\uc2b5\ub2c8\ub2e4.", "label": "0", "portion_identifier": -1, "text_b": "\uc774\uac83\uc740 \ub85c\ub4dc\uc544\uc77c\ub79c\ub4dc\uc5d0\uc11c \uc704\ud611\ubc1b\ub294 \uac83\ucc98\ub7fc, \ub9e4\uc0ac\ucd94\uc138\uce20\uc640 \ub274\ud584\ud504\uc154\uc5d0\uc11c\ucc98\ub7fc \ucf54\ub124\ud2f0\ucef7\uc5d0\uc11c \uc704\ud611\ubc1b\uace0 \ubc84\ubaac\ud2b8\uc5d0\uc11c \uc704\ud611\ubc1b\uc2b5\ub2c8\ub2e4."}, {"uid": "korean-1189-val", "text_a": "\uadf8\ub294 1824\ub144\uc5d0 \uc70c\ub9ac\uc5c4\uc2a4 \uce74\uc6b4\ud2f0\uc758 \uc9c0\ubc29\uac80\uc0ac\ub85c \uc784\uba85\ub418\uc5c8\uace0 1826\ub144\uc5d0 \uc138\ub124\uce74 \uce74\uc6b4\ud2f0, 18927\ub144\uc5d0 \uc0cc\ub354\uc2a4\ud0a4 \uce74\uc6b4\ud2f0\uc758 \uc9c0\ubc29\uac80\uc0ac\ub85c \uc784\uba85\ub418\uc5c8\uc2b5\ub2c8\ub2e4.", "label": "0", "portion_identifier": -1, "text_b": "\uadf8\ub294 1824\ub144 \uc138\ub124\uce74 \uce74\uc6b4\ud2f0\uc758 \uace0\uc18c\uc778 \ubcc0\ud638\uc0ac\ub85c \uc784\uba85\ub418\uc5c8\uace0 1826\ub144\uc5d0\ub294 \uc70c\ub9ac\uc5c4\uc2a4 \uce74\uc6b4\ud2f0, 1827\ub144\uc5d0\ub294 \uc0cc\ub354\uc2a4\ud0a4 \uce74\uc6b4\ud2f0\uc758 \uace0\uc18c\uc778 \ubcc0\ud638\uc0ac\ub85c \uc784\uba85\ub418\uc5c8\uc2b5\ub2c8\ub2e4."}, {"uid": "korean-377-val", "text_a": "\ub18d\uc5c5\uc5d0\uc11c \uadf8\uc758 \ub2e4\uc74c \uc791\uc5c5\uc740 \uc8fc\ub85c Norfolk\uc5d0\uc11c \uc774\ub904\uc84c\uc9c0\ub9cc \uadf8\ub294 \ub610\ud55c Lincolnshire\uc5d0 \uc788\ub294 \uc81c\ubc29 \ud655\uc7a5\uc744 \uc81c\uc548\ud588\uc73c\uba70 \uc774\uac83\uc740 \uc131\uacf5\uc801\uc73c\ub85c \uc2dc\ud589\ub418\uc5c8\uc2b5\ub2c8\ub2e4.", "label": "0", "portion_identifier": -1, "text_b": "\uc774\uc5b4\uc9c0\ub294 \uadf8\uc758 \uc774\uc5b4\uc9c0\ub294 \ub18d\uc5c5 \ubd84\uc57c\uc758 \uc791\uc5c5\uc740 \uc8fc\ub85c \ub9c1\ucee8\uc154\uc5d0\uc11c \uc9c4\ud589\ub418\uc5c8\uc73c\ub098 \ub178\ud37d\uc5d0\uc11c \ub300\uaddc\ubaa8\uc758 \uc81c\ubc29 \uacf5\uc0ac\ub97c \uc81c\uc548\ud588\uace0 \uc774\ub294 \uc131\uacf5\uc801\uc73c\ub85c \uc218\ud589\ub418\uc5c8\uc2b5\ub2c8\ub2e4."}, {"uid": "korean-1512-val", "text_a": "Clark\ub294 2007\ub144 4\uc6d4 3\uc77c\uc5d0 \ud0dc\uc5b4\ub09c \uc544\ub4e4 Rishi\uac00 \uc788\uc5c8\uc2b5\ub2c8\ub2e4. Microcosm Music\uc5d0\uc11c \ubc1c\ub9e4\ud55c Socks and Sandals EP\ub294 \uadf8\uc758 \uc544\ub4e4 Rishi Saturn\uc744 \ub530\ub77c \uba85\uba85\ud588\uc2b5\ub2c8\ub2e4.", "label": "0", "portion_identifier": -1, "text_b": "Rishi\uc5d0\uac8c\ub294 2007\ub144 4\uc6d4 3\uc77c\uc5d0 \ud0dc\uc5b4\ub09c \uc544\ub4e4 Clark\uc774 \uc788\uc5c8\uc2b5\ub2c8\ub2e4. \uc18c\uc6b0\uc8fc \uc74c\uc545\uc5d0 \uad00\ud55c Socks and Sandals EP\ub294 Rishi Saturn\uc758 \uc774\ub984\uc744 \ub530\ub77c \uba85\uba85\ub418\uc5c8\uc2b5\ub2c8\ub2e4."}], "1": [{"uid": "korean-1346-val", "text_a": "Alaja , , \ub294 \uce74\uc2a4\ud53c \ud574\uc758 \uc11c\ubd80 \ud22c\ub974\ud06c\uba54\ub2c8\uc2a4\ud0c4\uc758 \ubc1c\uce78 \uc9c0\ubc29\uc5d0 \uc788\ub294 \uc778\uad6c\uac00 \uc801\uc740 \uacf3\uc785\ub2c8\ub2e4.", "label": "1", "portion_identifier": -1, "text_b": "\uc54c\ub77c\ud558\ub294 \uce74\uc2a4\ud53c\ud574\uc758 \ud22c\ub974\ud06c\uba54\ub2c8\uc2a4\ud0c4 \uc11c\ucabd \ubc1c\uce78 \uc8fc\uc5d0 \uc788\ub294 \uc801\uc740 \uc778\uad6c\uc758 \uc7a5\uc18c\uc785\ub2c8\ub2e4."}, {"uid": "korean-559-val", "text_a": "\uc774 \uc885\uc740 \ud604\uc7ac \uc774\uad6c\uc544\ub098\uacfc, Polychrotinae\uc544\uacfc\ub77c\uace0 \uc54c\ub824\uc9c4 \ub3c4\ub9c8\ubc40\uacfc\uc774\uace0 \ub354 \uc774\uc0c1 \ud604\uc7ac \uc720\ud6a8\ud558\uc9c0 \uc54a\uc740 \uacfc\uc778 polychrotidae\ub85c \ubd84\ub958\ub418\uc9c0 \uc54a\uc2b5\ub2c8\ub2e4.", "label": "1", "portion_identifier": -1, "text_b": "\uc774 \uc18d\uc740 \ud604\uc7ac \uc774\uad6c\uc544\ub098\uacfc\ub85c \uc54c\ub824\uc9c4 \ub3c4\ub9c8\ubc40\uad70, \uc544\ub180\ub3c4\ub9c8\ubc40\uc544\uacfc\uc5d0 \uc18d\ud558\uba70 \ud604\uc7ac\ub294 \uc0ac\uc6a9\ud558\uc9c0 \uc54a\ub294 \ub364\ubd88\uc232\uc544\ub180\ub3c4\ub9c8\ubc40\uacfc\ub85c \ubd84\ub958\ub418\uc9c0 \uc54a\ub294\ub2e4."}, {"uid": "korean-1434-val", "text_a": "Ganj Basoda\ub294 \uc6b0\ub2e4\uc774\ud478\ub974 \uadfc\ucc98\uc758 \uc778\ub3c4 \uc8fc, \ub9c8\ub514\uc57c \ud504\ub77c\ub370\uc2dc\uc758 \ub9c8\uc744\uc785\ub2c8\ub2e4.", "label": "1", "portion_identifier": -1, "text_b": "Ganj Basoda\ub294 \uc778\ub3c4 \uc6b0\ub2e4\uc774\ud478\ub974 \uadfc\ucc98 \ub9c8\ub514\uc544 \ud504\ub77c\ub370\uc2dc\uc8fc\uc5d0 \uc788\ub294 \ub3c4\uc2dc\uc785\ub2c8\ub2e4."}, {"uid": "korean-1844-val", "text_a": "\ub85c\ub9c8 \uac00\ud1a8\ub9ad \uad50\uad6c Lugazi\ub294 \uc6b0\uac04\ub2e4, Kampala \uad50\ud68c \uc9c0\ubc29\uc758 Lugazi \uc2dc\uc5d0 \uc788\ub294 \uad50\uad6c\uc785\ub2c8\ub2e4.", "label": "1", "portion_identifier": -1, "text_b": "\ub8e8\uac00\uc9c0\uc758 \ub85c\ub9c8 \uce74\ud1a8\ub9ad \uad50\uad6c\ub294 \uc6b0\uac04\ub2e4\uc758 \uae30\ub3c5\uad50 \uc8fc\uc778 \uce84\ud314\ub77c\uc758 \ub8e8\uac00\uc9c0 \uc2dc\uc5d0 \uc788\ub294 \uad50\uad6c\uc785\ub2c8\ub2e4."}]}