{"0": [{"uid": "spanish-1965-val", "text_a": "El distrito franc\u00e9s de Finist\u00e8re es un 1.er distrito en el \"d\u00e9partement\" de Finist\u00e8re.", "label": "0", "portion_identifier": -1, "text_b": "El 1.er distrito de Finist\u00e8re es un distrito franc\u00e9s en el \"d\u00e9partement\" de Finist\u00e8re."}, {"uid": "spanish-460-val", "text_a": "Cuanto Platzer abri\u00f3 su segundo restaurante en Allentown en 1993, cambi\u00f3 el nombre a P. J. Whelihan's en honor a su abueno, Peter Joseph Whelihan.", "label": "0", "portion_identifier": -1, "text_b": "En 1993, cuando Peter Joseph Whelihan abri\u00f3 su segundo restaurante en Allentown, le cambi\u00f3 el nombre por P. J. Whelihan's en honor a su abuelo, Platzer."}], "1": [{"uid": "spanish-1312-val", "text_a": "\"Taunton Castle'' se present\u00f3 en Penang el 1 de agosto y en R\u00edo de Janeiro el 31 de octubre.", "label": "1", "portion_identifier": -1, "text_b": "El \"Castillo de Taunton'' estaba en Penang el 1 de agosto y el 31 de octubre en R\u00edo de Janeiro."}, {"uid": "spanish-241-val", "text_a": "Agreg\u00f3 que la violaci\u00f3n se produjo poco tiempo despu\u00e9s del incidente.", "label": "1", "portion_identifier": -1, "text_b": "Agreg\u00f3 que el abuso sexual ocurri\u00f3 poco tiempo despu\u00e9s de que se produjera el incidente mencionado."}]}