{"0": [{"uid": "german-1879-val", "text_a": "Dotty wurde 1923 in Gloucester geboren und starb 2014 in Boston.", "label": "0", "portion_identifier": -1, "text_b": "Dotty wurde 1923 in Boston geboren und starb 2014 in Gloucester."}], "1": [{"uid": "german-788-val", "text_a": "Im Januar 2013 wurde angek\u00fcndigt, dass Warren Spector nach der Schlie\u00dfung von Disney Interactive die Junction Point Studios verlassen hatte.", "label": "1", "portion_identifier": -1, "text_b": "Im Januar 2013 wurde bekanntgegeben, dass Warren Spector Junction Point Studios nach der Schlie\u00dfung von Disney Interactive verlassen hatte."}]}