{"contradiction": [{"uid": "german-6129-val", "text_a": "Nationale Einigkeit hat von da an immer die zweite Geige gespielt , nach ethnischen , religi\u00f6sen und vorallem regionalen \u00f6k\u00f6nomischen Interessen .", "label": "contradiction", "portion_identifier": -1, "text_b": "Nationale Einheit ist \u00fcberhaupt nicht von Bedeutung ."}], "entailment": [{"uid": "german-6273-val", "text_a": ", die Regional Haze RIA und die NOx SIP Call RIA ) , der niedrigste gesch\u00e4tze gesundheitssch\u00e4dliche Luftverschmutzungswert liegt bei 15 g / m3", "label": "entailment", "portion_identifier": -1, "text_b": "Sie sch\u00e4tzten die Vorteile ."}], "neutral": [{"uid": "german-5230-val", "text_a": "Oh , es war Snake River oh Snake River mit vielen Schlangen drin", "label": "neutral", "portion_identifier": -1, "text_b": "Snake River hat viele Schnappschildkr\u00f6ten ."}]}