{"contradiction": [{"uid": "german-6293-val", "text_a": "29 Daher sollten 21 Monate eine vern\u00fcnftige und in einigen F\u00e4llen eine vorsichtige Sch\u00e4tzung der Gesamtzeit sein , die erforderlich ist , um einen einzelnen Kraftwerkkessel f\u00fcr den Versorgungsbetrieb nachzur\u00fcsten .", "label": "contradiction", "portion_identifier": -1, "text_b": "Ein Boiler kann in wenigen Tagen nachger\u00fcstet werden ."}], "entailment": [{"uid": "german-7163-val", "text_a": "Die Boston Globe hat eine schwer-treffliche vier teilige Serie \u00fcber Harvard University publiziert .", "label": "entailment", "portion_identifier": -1, "text_b": "Der Boston Globe schrieb \u00fcber die Harvard University ."}], "neutral": [{"uid": "german-6428-val", "text_a": "Der Plan sollte auch die Erwerbsmethode identifizieren , go / no-go Kernpunkte , ein formaler Trainingsplan und ein Notfallplan zur Minimierung von Verlusten .", "label": "neutral", "portion_identifier": -1, "text_b": "Der Plan sollte auch ein Budget enthalten ."}]}