{"contradiction": [{"uid": "spanish-13873-val", "text_a": "Gestionar el cambio en las industrias postales y de env\u00edo , Ed .", "label": "contradiction", "portion_identifier": -1, "text_b": "El cambio en las Industrias de Correos y de Entrega ocurre de forma org\u00e1nica y no se tiene que gestionar ."}, {"uid": "spanish-13333-val", "text_a": "M\u00e1s fr\u00eda a\u00fan y m\u00e1s distante que nunca se alz\u00f3 la voz de su se\u00f1or\u00eda .", "label": "contradiction", "portion_identifier": -1, "text_b": "Su se\u00f1or\u00eda habl\u00f3 con calma a todos dando la impresi\u00f3n de ser una persona c\u00e1lida y amable ."}], "entailment": [{"uid": "spanish-14874-val", "text_a": "Dos de los escritores de historia popular m\u00e1s conocidos de Canad\u00e1 , Peter C. Newman y Pierre Berton , usan el t\u00e9rmino casi exclusivamente en los trabajos que han escrito sobre el norte de Canad\u00e1 .", "label": "entailment", "portion_identifier": -1, "text_b": "Peter C. Newman y Pierre Berton son escritores populares de la historia canadiense ."}, {"uid": "spanish-14306-val", "text_a": "\u00bf A\u00f1adir\u00e1s tus sue\u00f1os a los nuestros ?", "label": "entailment", "portion_identifier": -1, "text_b": "\u00bf Tus sue\u00f1os se convertir\u00e1n en parte de los nuestros ?"}], "neutral": [{"uid": "spanish-13780-val", "text_a": "Las estimaciones derivadas de los estudios sobre la exposici\u00f3n a largo plazo que justifican una parte importante de los beneficios del C\u00e1lculo Base no se ven afectadas .", "label": "neutral", "portion_identifier": -1, "text_b": "Las estimaciones incluyen la exposici\u00f3n a largo plazo , por lo que a corto plazo es probablemente mucho menor ."}, {"uid": "spanish-12895-val", "text_a": "S\u00ed , alg\u00fan grupo de inter\u00e9s especial .", "label": "neutral", "portion_identifier": -1, "text_b": "El grupo est\u00e1 interesado en temas ambientales ."}]}