{"0": [{"uid": "german-497-val", "text_a": "Die folgende Tabelle vergleicht die Leistung der LOD - f\u00e4higes Rendering und ein Rohling - Detailmethode (volle Kraft).", "label": "0", "portion_identifier": -1, "text_b": "In der folgenden Tabelle wird die Leistung von LOD-bewusster Wiedergabe und einer vollen Detailmethode (\u201eBruto Force\u201c) verglichen."}, {"uid": "german-771-val", "text_a": "Das Turnier gewann Gabriel Medina (BRA), der im Finale Joel Parkinson (AUS) schlug.", "label": "0", "portion_identifier": -1, "text_b": "Das Turnier wurde von Joel Parkinson (BRA) gewonnen, der im Finale Gabriel Medina (AUS) besiegte."}], "1": [{"uid": "german-1176-val", "text_a": "Ashte ist ein Dorf in Distrikt Palghar von Maharashtra, Indien. Es liegt in Dahanu Taluka.", "label": "1", "portion_identifier": -1, "text_b": "Ashte ist ein Dorf im Bezirk Palghar in Maharashtra, Indien. Es liegt in Dahanu Taluka."}, {"uid": "german-1001-val", "text_a": "Es war das 6. Event des Turniers und der dritte Stop der IRB Sevens World Series von 2013/2014.", "label": "1", "portion_identifier": -1, "text_b": "Es war die sechste Auflage des Turniers und der dritte Halt der IRB Sevens World Series 2013 -- 14."}]}