{"contradiction": [{"uid": "turkish-27670-val", "text_a": "Ulusal haberlerin yerel b\u00f6lgeyi nas\u0131l etkiledi\u011fine dikkat et", "label": "contradiction", "portion_identifier": -1, "text_b": "Yerel b\u00f6lgelerimiz hakk\u0131ndaki kayg\u0131lardan dolay\u0131 ulusal haberlerin konular\u0131n\u0131 daha az umursayamazd\u0131m ."}, {"uid": "turkish-29799-val", "text_a": "idari / hukuki batta , begar , chaprasi , dakoit , dakoity , dhan , dharna , kotwal , kotwali , panchayat , pottah , sabha", "label": "contradiction", "portion_identifier": -1, "text_b": "Kelimelerin hepsi kolay anla\u015f\u0131l\u0131yor ."}], "entailment": [{"uid": "turkish-29085-val", "text_a": "NYPD kayd\u0131 , \u00d6zel Operasyonlar B\u00f6l\u00fcm\u00fc radyo kanal\u0131 , 11 Eyl\u00fcl 2001 .", "label": "entailment", "portion_identifier": -1, "text_b": "Eyl\u00fcl ay\u0131nda baz\u0131 radyo yay\u0131n kay\u0131tlar\u0131 yap\u0131ld\u0131 ."}, {"uid": "turkish-27857-val", "text_a": "evet , Teksas ' ta bir tabanca ta\u015f\u0131mak yasal de\u011fil , ama hay\u0131r , evinizde buna sahip olamazs\u0131n\u0131z .", "label": "entailment", "portion_identifier": -1, "text_b": "Teksas ' ta evinizin d\u0131\u015f\u0131nda silah ta\u015f\u0131yamazs\u0131n\u0131z ."}], "neutral": [{"uid": "turkish-28053-val", "text_a": "O halde , obje dakikalarca makinede olmal\u0131 sonra makinede i\u015flenmeli ve bu \u015fekilde devam etmelidir .", "label": "neutral", "portion_identifier": -1, "text_b": "Obje dakikalar boyunca makinenin \u00fczerinde kalm\u0131yorsa patlar ."}, {"uid": "turkish-28602-val", "text_a": "Seyir liman\u0131n\u0131n yan\u0131nda Bayrak Tepesi , deniz seviyesinden 700 ft ( 214 m ) y\u00fckseliyor .", "label": "neutral", "portion_identifier": -1, "text_b": "Flag Hill , \u015fehrin geri kalan\u0131yla k\u0131yasland\u0131\u011f\u0131nda \u00e7ok y\u00fcksektir ."}]}