{"contradiction": [{"uid": "vietnamese-33179-val", "text_a": "\u0110\u1ea7y suy t\u01b0 , anh ta vu\u1ed1t ve b\u1ed9 r\u00e2u v\u00e0ng c\u1ee7a m\u00ecnh .", "label": "contradiction", "portion_identifier": -1, "text_b": "M\u1eb7t anh \u1ea5y \u0111\u00e3 \u0111\u01b0\u1ee3c c\u1ea1o s\u1ea1ch s\u1ebd ."}], "entailment": [{"uid": "vietnamese-33671-val", "text_a": "Ngo\u00e0i ra , nh\u00e2n vi\u00ean ch\u01b0\u01a1ng tr\u00ecnh c\u00f2n ti\u1ebfn h\u00e0nh nhi\u1ec1u lo\u1ea1i h\u1ed9i th\u1ea3o kh\u00e1c nhau v\u00e0 cung c\u1ea5p t\u00e0i li\u1ec7u gi\u00e1o d\u1ee5c cho c\u00e1c nh\u00e0 cung c\u1ea5p m\u1edbi .", "label": "entailment", "portion_identifier": -1, "text_b": "Nh\u00e2n s\u1ef1 ch\u01b0\u01a1ng tr\u00ecnh t\u1ed5 ch\u1ee9c c\u00e1c bu\u1ed5i h\u1ed9i th\u1ea3o ."}], "neutral": [{"uid": "vietnamese-34664-val", "text_a": "V\u00ed d\u1ee5 , m\u1ed9t s\u1ed1 c\u00f3 d\u1eabn xu\u1ea5t r\u00f5 r\u00e0ng lo\u1ea1i b\u1ecf kh\u1ecfi c\u00e1c thi\u1ebft b\u1ecb \u0111\u01b0\u1ee3c s\u1eed d\u1ee5ng ho\u1eb7c c\u01a1 s\u1edf m\u00e0 tr\u00ean \u0111\u00f3 c\u00e1c tr\u00f2 ch\u01a1i \u0111\u01b0\u1ee3c ch\u01a1i .", "label": "neutral", "portion_identifier": -1, "text_b": "\u0110i\u1ec1u n\u00e0y th\u01b0\u1eddng x\u1ea3y ra khi m\u00e0 m\u1ed9t m\u00f4n th\u1ec3 thao \u0111\u01b0\u1ee3c t\u1ea1o ra b\u1eb1ng c\u00e1ch d\u00f9ng c\u00e1c thi\u1ebft b\u1ecb s\u1eb5n c\u00f3 t\u1eeb c\u00e1c m\u00f4n th\u1ec3 thao kh\u00e1c ."}]}