{"1": [{"uid": "french-35221-trn", "text_a": "COMMANDE JAMAIS RE\u00c7U !!!! Indiqu\u00e9e livr\u00e9 et aucune r\u00e9ponse \u00e0 ma demande d\u2019explication", "label": 1, "portion_identifier": -1, "text_b": "COMMANDE JAMAIS RE\u00c7U . automotive"}], "2": [{"uid": "french-43847-trn", "text_a": "Ne fait pas ventilateur simple que de l air chaud", "label": 2, "portion_identifier": -1, "text_b": "Ne fait pas ventilateur . home_improvement"}], "3": [{"uid": "french-82307-trn", "text_a": "... dur\u00e9e de vie de ce c\u00e2ble assez courte (env. 5 mois) \u00c0 part \u00e7a, ce c\u00e2ble fait bien son boulot.", "label": 3, "portion_identifier": -1, "text_b": "Bien mais ... . electronics"}], "4": [{"uid": "french-128065-trn", "text_a": "Tr\u00e8s bon rapport qualit\u00e9 - Prix \u00e0 voir le vieillissement avec le temps.", "label": 4, "portion_identifier": -1, "text_b": "Conforme \u00e0 la description . wireless"}], "5": [{"uid": "french-171153-trn", "text_a": "C'est le premier sapin que j'ach\u00e8te pour mon premier appartement. J'ai choisi un sapin artificiel pour le garder durant des ann\u00e9es et celui ci fera tout \u00e0 fait le job ! Pli\u00e9 il tient dans un carton qui fait moins d'1m de haut, il se monte tr\u00e8s facilement (1 pied \u00e0 cliper sur un tron\u00e7on, puis 2 autres tron\u00e7ons \u00e0 ajouter). Les branches sont d\u00e9j\u00e0 sur les tron\u00e7ons il n'y a plus qu'\u00e0 les d\u00e9plier. Il n'est pas tr\u00e8s tr\u00e8s fournis mais c'est tout \u00e0 fait satisfaisant surtout en y ajoutant les d\u00e9cos. Les \u00e9pines font leur effet. Il est stable et fait bien son 1m80 ! Bref je le recommande vivement", "label": 5, "portion_identifier": -1, "text_b": "Tr\u00e8s bien ! . furniture"}]}