{"0": [{"uid": "french-409-val", "text_a": "Pennmakkkal est un film indien en malayalam de 1966 produit par J. Sasikumar et r\u00e9alis\u00e9 par KP Kottarakkara.", "label": "0", "portion_identifier": -1, "text_b": "Pennmakkkal est un film indien malayalam mis en sc\u00e8ne par J. Sasikumar et produit par KP Kottarakkara."}], "1": [{"uid": "french-396-val", "text_a": "Pauline dit oui, mais Frannie est toujours suspicieuse.", "label": "1", "portion_identifier": -1, "text_b": "Oui, dit Pauline, mais Frannie est toujours m\u00e9fiante."}]}